CMakeLists.txt
MANIFEST.in
README.md
pyproject.toml
setup.py
cpp/bindings.cpp
cpp/checks.hpp
cpp/launch.cpp
cpp/launch.hpp
cuda/arch_guard.cuh
cuda/epilogue.cuh
cuda/int4_gemm.cu
cuda/iterators.cuh
cuda/unpack.cuh
python/convert_llama.py
python/quantize.py
python/qgemm/__init__.py
python/qgemm.egg-info/PKG-INFO
python/qgemm.egg-info/SOURCES.txt
python/qgemm.egg-info/dependency_links.txt
python/qgemm.egg-info/requires.txt
python/qgemm.egg-info/top_level.txt
tests/test_op_parity.py
tests/test_outliers_fp16.py
tests/test_pack_unpack.py
tests/test_shapes.py