Metadata-Version: 2.4
Name: qgemm
Version: 0.0.2
Summary: INT4 quantization tooling and CUDA extension
Author: qgemm
License: Proprietary
Requires-Python: >=3.8
Requires-Dist: torch
Requires-Dist: safetensors
Requires-Dist: transformers
Requires-Dist: loguru
Requires-Dist: pyyaml
Requires-Dist: tqdm
